Metadata-Version: 1.0
Name: Flask-oDesk
Version: 0.4.1.1
Summary: Adds oDesk API support to Flask
Home-page: https://github.com/odesk/flask-odesk
Author: Volodymyr Hotsyk
Author-email: gotsyk@gmail.com
License: BSD
Download-URL: http://github.com/odesk/flask-odesk
Platform: any
Classifier: Development Status :: 4 - Beta
Classifier: Environment :: Web Environment
Classifier: Intended Audience :: Developers
Classifier: License :: OSI Approved :: BSD License
Classifier: Operating System :: OS Independent
Classifier: Programming Language :: Python
Classifier: Topic :: Internet :: WWW/HTTP :: Dynamic Content
Classifier: Topic :: Software Development :: Libraries :: Python Modules
